Metadata-Version: 2.1
Name: thumbor-extras
Version: 1.0.2
Summary: Some useful extensions to thumbor - extra filters and detectors.
Home-page: https://github.com/imaus10/thumbor_extras
Author: Austin Blanton
Author-email: imaus10@gmail.com
License: UNKNOWN
Platform: UNKNOWN
Classifier: Programming Language :: Python :: 2 :: Only
Classifier: License :: OSI Approved :: MIT License
Classifier: Operating System :: OS Independent
Requires-Dist: opencv-python
Requires-Dist: thumbor
